oats/__init__.py
oats/_data/__init__.py
oats/_data/base.py
oats/_data/ucrdata.py
oats/_utils/__init__.py
oats/_utils/dlutils.py
oats/_utils/utils.py
oats/_utils/visualizer.py
oats/generator/__init__.py
oats/generator/_base.py
oats/generator/univariate_wave.py
oats/models/__init__.py
oats/models/_base.py
oats/models/_darts_model.py
oats/models/_darts_simple.py
oats/models/_pyod_model.py
oats/models/distance/__init__.py
oats/models/distance/iforest.py
oats/models/distance/matrixprofile.py
oats/models/predictive/__init__.py
oats/models/predictive/arima.py
oats/models/predictive/fluxev.py
oats/models/predictive/lightgbm.py
oats/models/predictive/ma.py
oats/models/predictive/nbeats.py
oats/models/predictive/nhits.py
oats/models/predictive/randomforest.py
oats/models/predictive/regression.py
oats/models/predictive/rnn.py
oats/models/predictive/tcn.py
oats/models/predictive/tft.py
oats/models/predictive/transformer.py
oats/models/reconstruction/__init__.py
oats/models/reconstruction/tranad.py
oats/models/reconstruction/vae.py
oats/models/rule_based/__init__.py
oats/models/rule_based/quantile.py
oats/preprocessor/__init__.py
oats/preprocessor/_base.py
oats/preprocessor/spectral_residual.py
oats/scorer/.spot.py.swp
oats/scorer/__init__.py
oats/scorer/_base.py
oats/scorer/qualitative_metrics.py
oats/scorer/supervised_scorer.py
oats/threshold/__init__.py
oats/threshold/_base.py
oats/threshold/jenks.py
oats/threshold/pot.py
oats/threshold/quantile.py
oats/threshold/spot.py
pyoats-0.1.4.dist-info/LICENSE
pyoats-0.1.4.dist-info/METADATA
pyoats-0.1.4.dist-info/WHEEL
pyoats-0.1.4.dist-info/RECORD
