Metadata-Version: 2.1
Name: pyoats
Version: 0.1.4
Summary: Quick and Easy Time Series Outlier Detection
License: Apache-2.0
Author: Benjamin Ye
Author-email: benjamin.ye@georgian.io
Requires-Python: >=3.9,<3.12
Classifier: License :: OSI Approved :: Apache Software License
Classifier: Programming Language :: Python :: 3
Classifier: Programming Language :: Python :: 3.9
Classifier: Programming Language :: Python :: 3.10
Classifier: Programming Language :: Python :: 3.11
Requires-Dist: darts (==0.28.0)
Requires-Dist: jenkspy (>=0.2.4,<0.3.0)
Requires-Dist: keras (>=2.9.0,<3.0.0)
Requires-Dist: lightgbm (>=4.3.0,<5.0.0)
Requires-Dist: numpy (>=1.26.4,<2.0.0)
Requires-Dist: nvidia-cudnn-cu11 (==8.9.4.25)
Requires-Dist: optuna (>=2.10.1,<3.0.0)
Requires-Dist: pyod (==1.1.3)
Requires-Dist: pytorch-lightning (>=1.7,<2.0)
Requires-Dist: scipy (>=1.12.0,<2.0.0)
Requires-Dist: statsforecast (>=1.7.3,<2.0.0)
Requires-Dist: statsmodels (>=0.14.1,<0.15.0)
Requires-Dist: stumpy (>=1.12.0,<2.0.0)
Requires-Dist: tensorflow (==2.15.1) ; sys_platform != "darwin"
Requires-Dist: tensorflow-metal (==1.1.0) ; sys_platform == "darwin"
Requires-Dist: torch (>=2.3.0,<3.0.0)
Requires-Dist: tqdm (>=4.66.2,<5.0.0)
